{"_default": {"1": {"date_of_birth": 1967, "firstname": "Yannic", "lastname": "Heyer", "picture_path": "exampledata/pictures/js.jpg", "gender": "male", "ekg_tests": [3, 5], "maximalpuls": 173}, "2": {"date_of_birth": 1989, "firstname": "Julian", "lastname": "Huber", "picture_path": "exampledata/pictures/tb.jpg", "gender": "male", "ekg_tests": [1, 2], "maximalpuls": 173}, "3": {"date_of_birth": 1963, "firstname": "Max", "lastname": "Mustermann", "gender": "female", "picture_path": "uploaded_pictures\\Bode1.Ordnung_Messung_vergleich.png", "ekg_tests": [4], "maximalpuls": 158}}}